CONTRIBUTING.rst
HISTORY.rst
LICENSE
MANIFEST.in
README.rst
setup.cfg
setup.py
docs/Makefile
docs/conf.py
docs/contributing.rst
docs/history.rst
docs/index.rst
docs/installation.rst
docs/make.bat
docs/readme.rst
docs/usage.rst
spree/__init__.py
spree/exceptions.py
spree/spree.py
spree.egg-info/PKG-INFO
spree.egg-info/SOURCES.txt
spree.egg-info/dependency_links.txt
spree.egg-info/not-zip-safe
spree.egg-info/top_level.txt
tests/__init__.py
tests/conftest.py
tests/test_pagination.py
tests/test_spree.py
tests/responses/create_product.json
tests/responses/order-R123456789.json
tests/responses/orders.json
tests/responses/product-2.json
tests/responses/product-26.json
tests/responses/products.json
tests/responses/stock_item-4.json
tests/responses/stock_items.json
tests/responses/variant-ROR-00013.json