Metadata-Version: 1.1
Name: spree
Version: 0.3.0
Summary: Spree python api client
Home-page: https://github.com/fulfilio/python-spree
Author: Fulfil.IO Inc.
Author-email: info@fulfil.io
License: BSD license
Keywords: spree
Platform: UNKNOWN
Classifier: Development Status :: 2 - Pre-Alpha
Classifier: Intended Audience :: Developers
Classifier: License :: OSI Approved :: BSD License
Classifier: Natural Language :: English
Classifier: Programming Language :: Python :: 2
Classifier: Programming Language :: Python :: 2.6
Classifier: Programming Language :: Python :: 2.7
Classifier: Programming Language :: Python :: 3
Classifier: Programming Language :: Python :: 3.3
Classifier: Programming Language :: Python :: 3.4
Classifier: Programming Language :: Python :: 3.5
